myTrain/__init__.py
myTrain/train.py
myTrain-1.dist-info/LICENSE.txt
myTrain-1.dist-info/METADATA
myTrain-1.dist-info/WHEEL
myTrain-1.dist-info/entry_points.txt
myTrain-1.dist-info/top_level.txt
myTrain-1.dist-info/zip-safe
myTrain-1.dist-info/RECORD
